command_handler/__init__.py
command_handler/handler.py
command_handler/views.py
command_handler/command/__init__.py
command_handler/command/handler/__init__.py
command_handler/command/handler/exceptions.py
command_handler/command/handler/handler.py
command_handler/command/handler/registry.py
command_handler/request/__init__.py
command_handler/request/exceptions.py
command_handler/request/validator/__init__.py
command_handler/request/validator/exceptions.py
command_handler/request/validator/factory.py
command_handler/request/validator/validator.py
command_handler/request/validator/asserts/__init__.py
command_handler/request/validator/asserts/command.py
command_handler/request/validator/asserts/json.py
command_handler/request/validator/asserts/private_ip.py
tests/__init__.py
tests/handler.py
tests/views.py
tests/command/__init__.py
tests/command/handler/__init__.py
tests/command/handler/exceptions.py
tests/command/handler/handler.py
tests/command/handler/registry.py
tests/request/__init__.py
tests/request/exceptions.py
tests/request/validator/__init__.py
tests/request/validator/exceptions.py
tests/request/validator/factory.py
tests/request/validator/validator.py
tests/request/validator/asserts/__init__.py
tests/request/validator/asserts/command.py
tests/request/validator/asserts/json.py
tests/request/validator/asserts/private_ip.py
command_handler-1.2.1.dist-info/METADATA
command_handler-1.2.1.dist-info/WHEEL
command_handler-1.2.1.dist-info/top_level.txt
command_handler-1.2.1.dist-info/RECORD
