Metadata-Version: 2.1
Name: command-handler
Version: 1.2.1
Summary: Library for handling POST commands for Flask framework
Home-page: https://github.com/sacoding/commandHandler.py/
License: UNKNOWN
Platform: UNKNOWN
Requires-Python: >=3.6
Requires-Dist: Flask (<2,>=1.0)
Requires-Dist: jsonschema (<3,>=2.4)
